{
  "meta": {
    "id": "character_0",
    "spriteCount": 50,
    "description": "Character '0' - Stroke Skeletonized & Typographically Aligned",
    "coordinateSpace": "normalized_0_1"
  },
  "sprites": [
    {
      "x": 0.6444,
      "y": 0.6139,
      "z": 0.5,
      "a": 1.0,
      "b": 0
    },
    {
      "x": 0.6015,
      "y": 0.659,
      "z": 0.5,
      "a": 1.0,
      "b": 0
    },
    {
      "x": 0.5514,
      "y": 0.6838,
      "z": 0.5,
      "a": 1.0,
      "b": 0
    },
    {
      "x": 0.4911,
      "y": 0.6937,
      "z": 0.5,
      "a": 1.0,
      "b": 0
    },
    {
      "x": 0.4335,
      "y": 0.6807,
      "z": 0.5,
      "a": 1.0,
      "b": 0
    },
    {
      "x": 0.3836,
      "y": 0.6518,
      "z": 0.5,
      "a": 1.0,
      "b": 0
    },
    {
      "x": 0.3505,
      "y": 0.6048,
      "z": 0.5,
      "a": 1.0,
      "b": 0
    },
    {
      "x": 0.3361,
      "y": 0.5883,
      "z": 0.5,
      "a": 1.0,
      "b": 0
    },
    {
      "x": 0.3703,
      "y": 0.6386,
      "z": 0.5,
      "a": 1.0,
      "b": 0
    },
    {
      "x": 0.4188,
      "y": 0.6771,
      "z": 0.5,
      "a": 1.0,
      "b": 0
    },
    {
      "x": 0.4764,
      "y": 0.6937,
      "z": 0.5,
      "a": 1.0,
      "b": 0
    },
    {
      "x": 0.5388,
      "y": 0.6888,
      "z": 0.5,
      "a": 1.0,
      "b": 0
    },
    {
      "x": 0.5934,
      "y": 0.6649,
      "z": 0.5,
      "a": 1.0,
      "b": 0
    },
    {
      "x": 0.6305,
      "y": 0.6328,
      "z": 0.5,
      "a": 1.0,
      "b": 0
    },
    {
      "x": 0.6621,
      "y": 0.5813,
      "z": 0.5,
      "a": 1.0,
      "b": 0
    },
    {
      "x": 0.679,
      "y": 0.2964,
      "z": 0.5,
      "a": 1.0,
      "b": 0
    },
    {
      "x": 0.6838,
      "y": 0.3507,
      "z": 0.5,
      "a": 1.0,
      "b": 0
    },
    {
      "x": 0.6888,
      "y": 0.4131,
      "z": 0.5,
      "a": 1.0,
      "b": 0
    },
    {
      "x": 0.6841,
      "y": 0.4754,
      "z": 0.5,
      "a": 1.0,
      "b": 0
    },
    {
      "x": 0.6788,
      "y": 0.5297,
      "z": 0.5,
      "a": 1.0,
      "b": 0
    },
    {
      "x": 0.6888,
      "y": 0.4737,
      "z": 0.5,
      "a": 1.0,
      "b": 0
    },
    {
      "x": 0.6888,
      "y": 0.4133,
      "z": 0.5,
      "a": 1.0,
      "b": 0
    },
    {
      "x": 0.6888,
      "y": 0.353,
      "z": 0.5,
      "a": 1.0,
      "b": 0
    },
    {
      "x": 0.6791,
      "y": 0.2966,
      "z": 0.5,
      "a": 1.0,
      "b": 0
    },
    {
      "x": 0.3121,
      "y": 0.317,
      "z": 0.5,
      "a": 1.0,
      "b": 0
    },
    {
      "x": 0.3063,
      "y": 0.3757,
      "z": 0.5,
      "a": 1.0,
      "b": 0
    },
    {
      "x": 0.3063,
      "y": 0.4319,
      "z": 0.5,
      "a": 1.0,
      "b": 0
    },
    {
      "x": 0.3143,
      "y": 0.4931,
      "z": 0.5,
      "a": 1.0,
      "b": 0
    },
    {
      "x": 0.3212,
      "y": 0.5429,
      "z": 0.5,
      "a": 1.0,
      "b": 0
    },
    {
      "x": 0.3118,
      "y": 0.4906,
      "z": 0.5,
      "a": 1.0,
      "b": 0
    },
    {
      "x": 0.3112,
      "y": 0.4304,
      "z": 0.5,
      "a": 1.0,
      "b": 0
    },
    {
      "x": 0.3112,
      "y": 0.3701,
      "z": 0.5,
      "a": 1.0,
      "b": 0
    },
    {
      "x": 0.3131,
      "y": 0.3131,
      "z": 0.5,
      "a": 1.0,
      "b": 0
    },
    {
      "x": 0.5808,
      "y": 0.1437,
      "z": 0.5,
      "a": 1.0,
      "b": 0
    },
    {
      "x": 0.6293,
      "y": 0.1822,
      "z": 0.5,
      "a": 1.0,
      "b": 0
    },
    {
      "x": 0.659,
      "y": 0.2344,
      "z": 0.5,
      "a": 1.0,
      "b": 0
    },
    {
      "x": 0.6694,
      "y": 0.262,
      "z": 0.5,
      "a": 1.0,
      "b": 0
    },
    {
      "x": 0.6484,
      "y": 0.2063,
      "z": 0.5,
      "a": 1.0,
      "b": 0
    },
    {
      "x": 0.6163,
      "y": 0.1692,
      "z": 0.5,
      "a": 1.0,
      "b": 0
    },
    {
      "x": 0.462,
      "y": 0.1257,
      "z": 0.5,
      "a": 1.0,
      "b": 0
    },
    {
      "x": 0.4062,
      "y": 0.1467,
      "z": 0.5,
      "a": 1.0,
      "b": 0
    },
    {
      "x": 0.3609,
      "y": 0.1895,
      "z": 0.5,
      "a": 1.0,
      "b": 0
    },
    {
      "x": 0.3311,
      "y": 0.2416,
      "z": 0.5,
      "a": 1.0,
      "b": 0
    },
    {
      "x": 0.341,
      "y": 0.2252,
      "z": 0.5,
      "a": 1.0,
      "b": 0
    },
    {
      "x": 0.3708,
      "y": 0.1772,
      "z": 0.5,
      "a": 1.0,
      "b": 0
    },
    {
      "x": 0.4207,
      "y": 0.1421,
      "z": 0.5,
      "a": 1.0,
      "b": 0
    },
    {
      "x": 0.4729,
      "y": 0.1225,
      "z": 0.5,
      "a": 1.0,
      "b": 0
    },
    {
      "x": 0.5353,
      "y": 0.1274,
      "z": 0.5,
      "a": 1.0,
      "b": 0
    },
    {
      "x": 0.5297,
      "y": 0.1225,
      "z": 0.5,
      "a": 1.0,
      "b": 0
    },
    {
      "x": 0.4652,
      "y": 0.1225,
      "z": 0.5,
      "a": 1.0,
      "b": 0
    }
  ]
}