{
  "meta": {
    "id": "character_q_lower",
    "spriteCount": 50,
    "description": "Character 'q' - Stroke Skeletonized & Typographically Aligned",
    "coordinateSpace": "normalized_0_1"
  },
  "sprites": [
    {
      "x": 0.4972,
      "y": 0.6804,
      "z": 0.5,
      "a": 1.0,
      "b": 0
    },
    {
      "x": 0.4182,
      "y": 0.4462,
      "z": 0.5,
      "a": 1.0,
      "b": 0
    },
    {
      "x": 0.4182,
      "y": 0.4986,
      "z": 0.5,
      "a": 1.0,
      "b": 0
    },
    {
      "x": 0.4182,
      "y": 0.551,
      "z": 0.5,
      "a": 1.0,
      "b": 0
    },
    {
      "x": 0.4182,
      "y": 0.6035,
      "z": 0.5,
      "a": 1.0,
      "b": 0
    },
    {
      "x": 0.423,
      "y": 0.6539,
      "z": 0.5,
      "a": 1.0,
      "b": 0
    },
    {
      "x": 0.4375,
      "y": 0.6964,
      "z": 0.5,
      "a": 1.0,
      "b": 0
    },
    {
      "x": 0.4049,
      "y": 0.7322,
      "z": 0.5,
      "a": 1.0,
      "b": 0
    },
    {
      "x": 0.4386,
      "y": 0.6937,
      "z": 0.5,
      "a": 1.0,
      "b": 0
    },
    {
      "x": 0.4225,
      "y": 0.651,
      "z": 0.5,
      "a": 1.0,
      "b": 0
    },
    {
      "x": 0.4182,
      "y": 0.6004,
      "z": 0.5,
      "a": 1.0,
      "b": 0
    },
    {
      "x": 0.4182,
      "y": 0.5479,
      "z": 0.5,
      "a": 1.0,
      "b": 0
    },
    {
      "x": 0.4182,
      "y": 0.4955,
      "z": 0.5,
      "a": 1.0,
      "b": 0
    },
    {
      "x": 0.4182,
      "y": 0.4431,
      "z": 0.5,
      "a": 1.0,
      "b": 0
    },
    {
      "x": 0.6175,
      "y": 0.332,
      "z": 0.5,
      "a": 1.0,
      "b": 0
    },
    {
      "x": 0.5804,
      "y": 0.3691,
      "z": 0.5,
      "a": 1.0,
      "b": 0
    },
    {
      "x": 0.5405,
      "y": 0.3746,
      "z": 0.5,
      "a": 1.0,
      "b": 0
    },
    {
      "x": 0.4949,
      "y": 0.3581,
      "z": 0.5,
      "a": 1.0,
      "b": 0
    },
    {
      "x": 0.4484,
      "y": 0.3725,
      "z": 0.5,
      "a": 1.0,
      "b": 0
    },
    {
      "x": 0.4269,
      "y": 0.3879,
      "z": 0.5,
      "a": 1.0,
      "b": 0
    },
    {
      "x": 0.469,
      "y": 0.3629,
      "z": 0.5,
      "a": 1.0,
      "b": 0
    },
    {
      "x": 0.5174,
      "y": 0.3629,
      "z": 0.5,
      "a": 1.0,
      "b": 0
    },
    {
      "x": 0.5606,
      "y": 0.3851,
      "z": 0.5,
      "a": 1.0,
      "b": 0
    },
    {
      "x": 0.5673,
      "y": 0.4347,
      "z": 0.5,
      "a": 1.0,
      "b": 0
    },
    {
      "x": 0.5673,
      "y": 0.4871,
      "z": 0.5,
      "a": 1.0,
      "b": 0
    },
    {
      "x": 0.5673,
      "y": 0.5396,
      "z": 0.5,
      "a": 1.0,
      "b": 0
    },
    {
      "x": 0.5673,
      "y": 0.592,
      "z": 0.5,
      "a": 1.0,
      "b": 0
    },
    {
      "x": 0.5673,
      "y": 0.6444,
      "z": 0.5,
      "a": 1.0,
      "b": 0
    },
    {
      "x": 0.5529,
      "y": 0.6869,
      "z": 0.5,
      "a": 1.0,
      "b": 0
    },
    {
      "x": 0.5673,
      "y": 0.7333,
      "z": 0.5,
      "a": 1.0,
      "b": 0
    },
    {
      "x": 0.5673,
      "y": 0.7858,
      "z": 0.5,
      "a": 1.0,
      "b": 0
    },
    {
      "x": 0.5673,
      "y": 0.8382,
      "z": 0.5,
      "a": 1.0,
      "b": 0
    },
    {
      "x": 0.5513,
      "y": 0.884,
      "z": 0.5,
      "a": 1.0,
      "b": 0
    },
    {
      "x": 0.5143,
      "y": 0.921,
      "z": 0.5,
      "a": 1.0,
      "b": 0
    },
    {
      "x": 0.5421,
      "y": 0.8933,
      "z": 0.5,
      "a": 1.0,
      "b": 0
    },
    {
      "x": 0.5791,
      "y": 0.8798,
      "z": 0.5,
      "a": 1.0,
      "b": 0
    },
    {
      "x": 0.6162,
      "y": 0.9168,
      "z": 0.5,
      "a": 1.0,
      "b": 0
    },
    {
      "x": 0.5969,
      "y": 0.8975,
      "z": 0.5,
      "a": 1.0,
      "b": 0
    },
    {
      "x": 0.5673,
      "y": 0.8573,
      "z": 0.5,
      "a": 1.0,
      "b": 0
    },
    {
      "x": 0.5673,
      "y": 0.8049,
      "z": 0.5,
      "a": 1.0,
      "b": 0
    },
    {
      "x": 0.5673,
      "y": 0.7524,
      "z": 0.5,
      "a": 1.0,
      "b": 0
    },
    {
      "x": 0.5608,
      "y": 0.7027,
      "z": 0.5,
      "a": 1.0,
      "b": 0
    },
    {
      "x": 0.5589,
      "y": 0.66,
      "z": 0.5,
      "a": 1.0,
      "b": 0
    },
    {
      "x": 0.5673,
      "y": 0.6111,
      "z": 0.5,
      "a": 1.0,
      "b": 0
    },
    {
      "x": 0.5673,
      "y": 0.5587,
      "z": 0.5,
      "a": 1.0,
      "b": 0
    },
    {
      "x": 0.5673,
      "y": 0.5062,
      "z": 0.5,
      "a": 1.0,
      "b": 0
    },
    {
      "x": 0.5673,
      "y": 0.4538,
      "z": 0.5,
      "a": 1.0,
      "b": 0
    },
    {
      "x": 0.5673,
      "y": 0.4014,
      "z": 0.5,
      "a": 1.0,
      "b": 0
    },
    {
      "x": 0.588,
      "y": 0.3615,
      "z": 0.5,
      "a": 1.0,
      "b": 0
    },
    {
      "x": 0.6251,
      "y": 0.3244,
      "z": 0.5,
      "a": 1.0,
      "b": 0
    }
  ]
}